autonl/__init__.py
autonl/cli.py
autonl-0.1.1.dist-info/LICENSE
autonl-0.1.1.dist-info/METADATA
autonl-0.1.1.dist-info/WHEEL
autonl-0.1.1.dist-info/entry_points.txt
autonl-0.1.1.dist-info/top_level.txt
autonl-0.1.1.dist-info/RECORD
